gemmm/__init__.py
gemmm/fetch_data.py
gemmm/model.py
gemmm/tables.py
gemmm/data/__init__.py
gemmm/data/msoa_table.parquet
gemmm-1.0.0.dist-info/licenses/LICENSE.txt
gemmm-1.0.0.dist-info/METADATA
gemmm-1.0.0.dist-info/WHEEL
gemmm-1.0.0.dist-info/top_level.txt
gemmm-1.0.0.dist-info/RECORD
