Metadata-Version: 2.4
Name: gemmm
Version: 1.0.0
Summary: Generating origin-destination matrices in Python
Author-email: Jonty Carruthers <jonathan.carruthers@ukhsa.gov.uk>
Project-URL: Homepage, https://github.com/ukhsa-collaboration/gemmm
Requires-Python: >=3.11
License-File: LICENSE.txt
Requires-Dist: setuptools>=75.8.0
Requires-Dist: numpy>=2.0.1
Requires-Dist: pandas>=2.2.2
Requires-Dist: scipy>=1.14.0
Requires-Dist: dask[distributed]>=2024.8.0
Requires-Dist: pyarrow>=17.0.0
Requires-Dist: pooch>=1.8.2
Requires-Dist: netCDF4>=1.6.0
Requires-Dist: h5py>=3.11.0
Requires-Dist: tqdm>=4.66.5
Requires-Dist: pip-system-certs>=4.0
Dynamic: license-file
